{"nodes": [{"id": "preprocessor", "label": "preprocessor.py", "file_type": "code", "source_file": "src/tools/preprocessor.py", "source_location": "L1"}, {"id": "preprocessor_is_auto_generated_file", "label": "is_auto_generated_file()", "file_type": "code", "source_file": "src/tools/preprocessor.py", "source_location": "L4"}, {"id": "preprocessor_rationale_5", "label": "Check if a file content looks like it was auto-generated.     Looks for @Generat", "file_type": "rationale", "source_file": "src/tools/preprocessor.py", "source_location": "L5"}], "edges": [{"source": "preprocessor", "target": "re", "relation": "imports", "confidence": "EXTRACTED", "source_file": "src/tools/preprocessor.py", "source_location": "L1", "weight": 1.0}, {"source": "preprocessor", "target": "preprocessor_is_auto_generated_file", "relation": "contains", "confidence": "EXTRACTED", "source_file": "src/tools/preprocessor.py", "source_location": "L4", "weight": 1.0}, {"source": "preprocessor_rationale_5", "target": "preprocessor_is_auto_generated_file", "relation": "rationale_for", "confidence": "EXTRACTED", "source_file": "src/tools/preprocessor.py", "source_location": "L5", "weight": 1.0}]}